atcoder/__init__.py
atcoder/__main__.py
atcoder/_bit.py
atcoder/_math.py
atcoder/_scc.py
atcoder/convolution.py
atcoder/dsu.py
atcoder/fenwicktree.py
atcoder/lazysegtree.py
atcoder/math.py
atcoder/maxflow.py
atcoder/mincostflow.py
atcoder/modint.py
atcoder/scc.py
atcoder/segtree.py
atcoder/string.py
atcoder/twosat.py
benchmarks/__init__.py
benchmarks/benchmark_dsu.py
example/__init__.py
example/convolution_practice.py
example/convolution_practice_int.py
example/dsu_practice.py
example/fenwick_practice.py
example/floor_sum_practice.py
example/lazysegtree_practice_k.py
example/lazysegtree_practice_k_wo_modint.py
example/lazysegtree_practice_l.py
example/maxflow_practice.py
example/mincostflow_practice.py
example/sa_practice.py
example/scc_practice.py
example/segtree_practice.py
example/segtree_practice_reversed.py
example/twosat_practice.py
tests/__init__.py
tests/test__bit.py
tests/test_dsu.py
tests/test_fenwicktree.py
tests/test_internal_math.py
tests/test_math.py
tests/example_tests/__init__.py
tests/example_tests/test_examples.py
ac_library_python-0.1.0.dist-info/LICENSE
ac_library_python-0.1.0.dist-info/METADATA
ac_library_python-0.1.0.dist-info/WHEEL
ac_library_python-0.1.0.dist-info/top_level.txt
ac_library_python-0.1.0.dist-info/RECORD
